shepherd/__init__.py
shepherd/__main__.py
shepherd/config.py
shepherd/py.typed
shepherd/cli/__init__.py
shepherd/cli/config.py
shepherd/cli/langfuse.py
shepherd/cli/main.py
shepherd/cli/sessions.py
shepherd/cli/shell.py
shepherd/models/__init__.py
shepherd/models/langfuse.py
shepherd/models/session.py
shepherd/providers/__init__.py
shepherd/providers/aiobs.py
shepherd/providers/langfuse.py
shepherd_cli-0.0.2.dist-info/METADATA
shepherd_cli-0.0.2.dist-info/WHEEL
shepherd_cli-0.0.2.dist-info/entry_points.txt
shepherd_cli-0.0.2.dist-info/licenses/LICENSE
shepherd_cli-0.0.2.dist-info/RECORD
